{
  "id": "S00PacketServerInfo",
  "hex": "0x00",
  "dec": 0,
  "dir": "CLIENTBOUND",
  "state": "STATUS",
  "name": "Server Status",
  "desc": "Responds to C00PacketServerQuery with the server's status as a JSON string (MOTD, players, version, favicon, mod info).",
  "tags": [
    "status",
    "server",
    "ping"
  ],
  "fields": [
    {
      "name": "jsonResponse",
      "type": "String (JSON)",
      "desc": "JSON-encoded ServerStatusResponse with version, players, description, favicon"
    }
  ],
  "encoding": [
    [
      "JSON Response",
      "String",
      "JSON ServerStatusResponse serialized to string"
    ]
  ],
  "mcp": [
    "NetHandlerStatusClient.handleServerInfo()"
  ],
  "handler": "INetHandlerStatusClient",
  "notes": "The JSON response includes: version (name + protocol number), players (max + online + optional sample list), description (MOTD ChatComponent), and optionally favicon (base64-encoded PNG with 'data:image/png;base64,' prefix). For modded servers, may include Forge mod info.",
  "implementation": {
    "modules": [
      {
        "name": "ServerInfo",
        "found_in": [],
        "purpose": "Read server info JSON (MOTD, players, version) for server detection.",
        "how_it_works": "",
        "vanilla_hook": "EventReceivePacket"
      },
      {
        "name": "BrandDetector",
        "found_in": [],
        "purpose": "Read server info JSON (MOTD, players, version) for server detection.",
        "how_it_works": "",
        "vanilla_hook": "EventReceivePacket"
      }
    ]
  }
}