{
  "id": "S0FPacketSpawnMob",
  "hex": "0x0F",
  "dec": 15,
  "dir": "CLIENTBOUND",
  "state": "PLAY",
  "name": "Spawn Mob",
  "desc": "Spawns a living entity (mob/animal/monster) with entity type, position, rotation, velocity, and metadata.",
  "tags": [
    "entity",
    "mob",
    "spawn",
    "creature"
  ],
  "fields": [
    {
      "name": "entityId",
      "type": "VarInt",
      "desc": "Entity ID"
    },
    {
      "name": "type",
      "type": "unsigned byte",
      "desc": "Mob type (50=creeper, 51=skeleton, 52=spider, 54=zombie, etc.)"
    },
    {
      "name": "x/y/z",
      "type": "fixed-point int",
      "desc": "Position × 32"
    },
    {
      "name": "yaw/pitch/headYaw",
      "type": "byte",
      "desc": "Rotations × 256/360"
    },
    {
      "name": "velocityX/Y/Z",
      "type": "short",
      "desc": "Velocity × 8000"
    },
    {
      "name": "metadata",
      "type": "DataWatcher",
      "desc": "Entity data watcher"
    }
  ],
  "encoding": [
    [
      "Entity ID",
      "VarInt",
      ""
    ],
    [
      "Type",
      "Unsigned Byte",
      "EntityList ID"
    ],
    [
      "X",
      "Int",
      "x * 32"
    ],
    [
      "Y",
      "Int",
      "y * 32"
    ],
    [
      "Z",
      "Int",
      "z * 32"
    ],
    [
      "Yaw",
      "byte",
      "yaw * 256/360"
    ],
    [
      "Pitch",
      "byte",
      "pitch * 256/360"
    ],
    [
      "Head Pitch",
      "byte",
      "headYaw * 256/360"
    ],
    [
      "Velocity X",
      "short",
      ""
    ],
    [
      "Velocity Y",
      "short",
      ""
    ],
    [
      "Velocity Z",
      "short",
      ""
    ],
    [
      "Metadata",
      "DataWatcher",
      ""
    ]
  ],
  "mcp": [
    "NetHandlerPlayClient.handleSpawnMob()"
  ],
  "handler": "INetHandlerPlayClient",
  "notes": "Entity types: 50=creeper, 51=skeleton, 52=spider, 53=giant, 54=zombie, 55=slime, 56=ghast, 57=zombiePigman, 58=enderman, 59=caveSpider, 60=silverfish, 61=blaze, 62=magmaCube, 63=enderDragon, 64=wither, 65=bats, 66=witch, 67=endermite, 68=guardian, 69=shulker, 90=pig, 91=sheep, 92=cow, 93=chicken, 94=squid, 95=wolf, 96=mooshroom, 97=snowman, 98=ocelot, 99=ironGolem, 100=horse, 101=rabbit, 120=villager.",
  "implementation": {
    "modules": [
      {
        "name": "ESP",
        "found_in": [
          "Tenacity 6.0",
          "Sigma 3.9",
          "Gugustus"
        ],
        "purpose": "Detect mob spawns. KillAura adds to target list. AntiBot filters mobs for bot detection. ESP shows mob info.",
        "how_it_works": "",
        "vanilla_hook": "EventReceivePacket"
      },
      {
        "name": "AntiBot",
        "found_in": [
          "Tenacity 6.0",
          "Sigma 3.9",
          "Gugustus"
        ],
        "purpose": "Detect mob spawns. KillAura adds to target list. AntiBot filters mobs for bot detection. ESP shows mob info.",
        "how_it_works": "",
        "vanilla_hook": "EventReceivePacket"
      },
      {
        "name": "Tracers",
        "found_in": [
          "Tenacity 6.0",
          "Sigma 3.9",
          "Gugustus"
        ],
        "purpose": "Detect mob spawns. KillAura adds to target list. AntiBot filters mobs for bot detection. ESP shows mob info.",
        "how_it_works": "",
        "vanilla_hook": "EventReceivePacket"
      },
      {
        "name": "KillAura",
        "found_in": [
          "Tenacity 6.0",
          "Sigma 3.9",
          "Gugustus"
        ],
        "purpose": "Detect mob spawns. KillAura adds to target list. AntiBot filters mobs for bot detection. ESP shows mob info.",
        "how_it_works": "",
        "vanilla_hook": "EventReceivePacket"
      }
    ]
  }
}