{
  "id": "S26PacketMapChunkBulk",
  "hex": "0x26",
  "dec": 38,
  "dir": "CLIENTBOUND",
  "state": "PLAY",
  "name": "Map Chunk Bulk",
  "desc": "Sends multiple chunks at once. Used for initial world load and large area updates.",
  "tags": [
    "world",
    "chunk"
  ],
  "fields": [
    {
      "name": "chunks",
      "type": "Chunk[]",
      "desc": "Array of chunk data with X/Z/bitmask/compressed data"
    },
    {
      "name": "skyLightSent",
      "type": "boolean",
      "desc": "Whether skylight data is included"
    }
  ],
  "encoding": [
    [
      "Sky Light",
      "bool",
      "Includes skylight"
    ],
    [
      "Column Count",
      "VarInt",
      ""
    ],
    [
      "Per Column",
      "int,int,short,VarInt,byte[]",
      "X, Z, bitmask, dataSize, compressed data"
    ]
  ],
  "mcp": [
    "NetHandlerPlayClient.handleMapChunkBulk()"
  ],
  "handler": "INetHandlerPlayClient",
  "notes": "S26 is the bulk version of S21 — sends many chunks in a single packet. Used on world join and loading large areas. XRay modules also cancel S26 alongside S21 to prevent chunk updates.",
  "implementation": {
    "modules": [
      {
        "name": "XRay",
        "found_in": [
          "Tenacity 6.0"
        ],
        "purpose": "Same as S21 but for bulk chunk loading. XRay modifies bulk data.",
        "how_it_works": "",
        "vanilla_hook": "EventReceivePacket"
      },
      {
        "name": "Search",
        "found_in": [
          "Tenacity 6.0"
        ],
        "purpose": "Same as S21 but for bulk chunk loading. XRay modifies bulk data.",
        "how_it_works": "",
        "vanilla_hook": "EventReceivePacket"
      }
    ]
  }
}